tests/__init__.py
tests/batch_test.py
tests/boil_test.py
tests/e41_test.py
tests/fgas_test.py
tests/flow_test.py
tests/jpump_test.py
tests/outflow_test.py
tests/pvt_test.py
tests/rmix_test.py
tests/wprof_test.py
woffl/__init__.py
woffl/assembly/__init__.py
woffl/assembly/batchrun.py
woffl/assembly/curvefit.py
woffl/assembly/network.py
woffl/assembly/sysops.py
woffl/flow/__init__.py
woffl/flow/annflow.py
woffl/flow/inflow.py
woffl/flow/jetflow.py
woffl/flow/jetgraphs.py
woffl/flow/jetplot.py
woffl/flow/outflow.py
woffl/flow/singlephase.py
woffl/flow/twophase.py
woffl/geometry/__init__.py
woffl/geometry/forms.py
woffl/geometry/jetpump.py
woffl/geometry/pipe.py
woffl/geometry/wellprofile.py
woffl/pvt/__init__.py
woffl/pvt/blackoil.py
woffl/pvt/deadoil.py
woffl/pvt/formgas.py
woffl/pvt/formwat.py
woffl/pvt/resmix.py
woffl-1.0.20.dist-info/LICENSE
woffl-1.0.20.dist-info/METADATA
woffl-1.0.20.dist-info/WHEEL
woffl-1.0.20.dist-info/top_level.txt
woffl-1.0.20.dist-info/RECORD
