Metadata-Version: 2.1
Name: woffl
Version: 1.0.20
Summary: Water Optimization For Fluid Lift. Numerical solver for liquid powered jet pumps with multiphase flow
License: MIT License
Project-URL: Homepage, https://github.com/kwellis/woffl
Keywords: jet pump,solver,numerical,multiphase
Classifier: Development Status :: 3 - Alpha
Classifier: Programming Language :: Python :: 3
Classifier: Intended Audience :: Science/Research
Classifier: Topic :: Scientific/Engineering :: Physics
Classifier: License :: OSI Approved :: MIT License
Requires-Python: >=3.10
License-File: LICENSE
Requires-Dist: matplotlib>=3.8.2
Requires-Dist: numpy>=1.26.3
Requires-Dist: pandas>=2.1.4
Requires-Dist: scipy>=1.11.4
Provides-Extra: dev
Requires-Dist: bumpver; extra == "dev"
Requires-Dist: isort; extra == "dev"
Requires-Dist: black; extra == "dev"
